odoo/addons/helpdesk_mgmt_rating/README.rst
odoo/addons/helpdesk_mgmt_rating/__init__.py
odoo/addons/helpdesk_mgmt_rating/__manifest__.py
odoo/addons/helpdesk_mgmt_rating/data/helpdesk_data.xml
odoo/addons/helpdesk_mgmt_rating/i18n/es.po
odoo/addons/helpdesk_mgmt_rating/i18n/es_AR.po
odoo/addons/helpdesk_mgmt_rating/i18n/fr.po
odoo/addons/helpdesk_mgmt_rating/i18n/helpdesk_mgmt_rating.pot
odoo/addons/helpdesk_mgmt_rating/i18n/it.po
odoo/addons/helpdesk_mgmt_rating/i18n/pt.po
odoo/addons/helpdesk_mgmt_rating/i18n/pt_BR.po
odoo/addons/helpdesk_mgmt_rating/i18n/sv.po
odoo/addons/helpdesk_mgmt_rating/models/__init__.py
odoo/addons/helpdesk_mgmt_rating/models/helpdesk_ticket.py
odoo/addons/helpdesk_mgmt_rating/models/helpdesk_ticket_stage.py
odoo/addons/helpdesk_mgmt_rating/readme/CONFIGURE.md
odoo/addons/helpdesk_mgmt_rating/readme/CONTRIBUTORS.md
odoo/addons/helpdesk_mgmt_rating/readme/DESCRIPTION.md
odoo/addons/helpdesk_mgmt_rating/static/description/icon.png
odoo/addons/helpdesk_mgmt_rating/static/description/index.html
odoo/addons/helpdesk_mgmt_rating/tests/__init__.py
odoo/addons/helpdesk_mgmt_rating/tests/test_helpdesk_mgmt_rating.py
odoo/addons/helpdesk_mgmt_rating/tests/test_helpdesk_portal.py
odoo/addons/helpdesk_mgmt_rating/views/helpdesk_ticket_menu.xml
odoo/addons/helpdesk_mgmt_rating/views/helpdesk_ticket_stage_views.xml
odoo/addons/helpdesk_mgmt_rating/views/helpdesk_ticket_views.xml
odoo_addon_helpdesk_mgmt_rating-18.0.1.0.0.3.dist-info/METADATA
odoo_addon_helpdesk_mgmt_rating-18.0.1.0.0.3.dist-info/WHEEL
odoo_addon_helpdesk_mgmt_rating-18.0.1.0.0.3.dist-info/top_level.txt
odoo_addon_helpdesk_mgmt_rating-18.0.1.0.0.3.dist-info/RECORD
